{
  "activity_info": {
    "activity_id": "2497821",
    "activity_type": "",
    "duration_minutes": "792",
    "end_time": "2025-01-21T22:09:04+03:00",
    "endless_event_id": "497330937",
    "endless_event_name": "Первая встреча",
    "endless_event_owner_id": "",
    "event_session_id": "",
    "has_transcript": "False",
    "is_recorded": "False",
    "participants_count_api": "0",
    "participants_count_csv": "9",
    "recordings_count": "0",
    "room_name": "Первая встреча",
    "start_time": "2025-01-21T08:56:08+03:00",
    "status": "",
    "transcripts_count": "0",
    "unique_participants": "0",
    "user_id": "111868709",
    "user_name": "Кристина Лучинина"
  },
  "analysis_timestamp": "2025-11-18T14:41:35.821974"
}